fastapi_route_middleware/__init__.py
fastapi_route_middleware-0.1.0.dist-info/METADATA
fastapi_route_middleware-0.1.0.dist-info/WHEEL
fastapi_route_middleware-0.1.0.dist-info/licenses/LICENSE
fastapi_route_middleware-0.1.0.dist-info/RECORD
