Metadata-Version: 2.4
Name: fastapi_route_middleware
Version: 0.1.0
Summary: A decorator-based middleware system for adding middleware to specific FastAPI routes
Project-URL: Homepage, https://github.com/lucamattiazzi/fastapi_route_middleware
Project-URL: Repository, https://github.com/lucamattiazzi/fastapi_route_middleware
Project-URL: Issues, https://github.com/lucamattiazzi/fastapi_route_middleware/issues
Author-email: Luca Mattiazzi <l.d.mattiazzi@gmail.com>
License: MIT
License-File: LICENSE
Keywords: async,decorator,fastapi,middleware,web
Classifier: Development Status :: 4 - Beta
Classifier: Framework :: FastAPI
Classifier: Intended Audience :: Developers
Classifier: License :: OSI Approved :: MIT License
Classifier: Programming Language :: Python :: 3
Classifier: Programming Language :: Python :: 3.8
Classifier: Programming Language :: Python :: 3.9
Classifier: Programming Language :: Python :: 3.10
Classifier: Programming Language :: Python :: 3.11
Classifier: Programming Language :: Python :: 3.12
Classifier: Programming Language :: Python :: 3.13
Classifier: Topic :: Internet :: WWW/HTTP
Classifier: Topic :: Software Development :: Libraries :: Python Modules
Requires-Python: >=3.8
